ghost_xarray/__init__.py
ghost_xarray/ghost_xarray.py
tests/test_open.py
ghost_xarray-0.3.1.dist-info/LICENSE
ghost_xarray-0.3.1.dist-info/METADATA
ghost_xarray-0.3.1.dist-info/WHEEL
ghost_xarray-0.3.1.dist-info/top_level.txt
ghost_xarray-0.3.1.dist-info/RECORD
