Metadata-Version: 2.1
Name: ghost-xarray
Version: 0.3.1
Summary: Load GHOST output files with xarray.
Author-email: Mauro Silberberg <maurosilber@gmail.com>
License: MIT License        
Project-URL: Homepage, https://github.com/maurosilber/ghost-xarray
Project-URL: Bug Tracker, https://github.com/maurosilber/ghost-xarray/issues
Keywords: GHOST,xarray
Classifier: Programming Language :: Python :: 3
Classifier: License :: OSI Approved :: MIT License
Classifier: Operating System :: OS Independent
Requires-Python: >=3.7
License-File: LICENSE
Requires-Dist: dask
Requires-Dist: numpy
Requires-Dist: xarray
Requires-Dist: cached-property ; python_version < "3.8"
Provides-Extra: test
Requires-Dist: pytest ; extra == 'test'
